mdvwhole/__init__.py
mdvwhole/whole.py
mdvwhole-0.0.7.1.dist-info/LICENSE
mdvwhole-0.0.7.1.dist-info/METADATA
mdvwhole-0.0.7.1.dist-info/WHEEL
mdvwhole-0.0.7.1.dist-info/entry_points.txt
mdvwhole-0.0.7.1.dist-info/top_level.txt
mdvwhole-0.0.7.1.dist-info/RECORD
