Metadata-Version: 2.1
Name: mdvwhole
Version: 0.0.7.1
Summary: A small package for making point cloud objects whole in the presence of PBC
Home-page: https://github.com/BartBruininks/mdvwhole
Author: BMH Bruininks, TA Wassenaar
Author-email: bartbruininks@gmail.com
Project-URL: Bug Tracker, https://github.com/BartBruininks/mdvwhole/issues
Classifier: Programming Language :: Python :: 3
Classifier: License :: OSI Approved :: Apache Software License
Classifier: Operating System :: OS Independent
Requires-Python: >=3.8
License-File: LICENSE
Requires-Dist: argparse
Requires-Dist: scipy
Requires-Dist: numpy
Requires-Dist: mdvoxelsegmentation
Requires-Dist: networkx
